{"nodes": [{"id": "c_users_surface_desktop_classora_lms_classora_lms_accounts_admin_py", "label": "admin.py", "file_type": "code", "source_file": "C:\\Users\\surface\\Desktop\\classora-lms\\classora-lms\\accounts\\admin.py", "source_location": "L1"}, {"id": "accounts_admin_instituteadmin", "label": "InstituteAdmin", "file_type": "code", "source_file": "C:\\Users\\surface\\Desktop\\classora-lms\\classora-lms\\accounts\\admin.py", "source_location": "L8"}, {"id": "accounts_admin_customuseradmin", "label": "CustomUserAdmin", "file_type": "code", "source_file": "C:\\Users\\surface\\Desktop\\classora-lms\\classora-lms\\accounts\\admin.py", "source_location": "L14"}, {"id": "baseuseradmin", "label": "BaseUserAdmin", "file_type": "code", "source_file": "", "source_location": ""}], "edges": [{"source": "c_users_surface_desktop_classora_lms_classora_lms_accounts_admin_py", "target": "django_contrib", "relation": "imports_from", "confidence": "EXTRACTED", "source_file": "C:\\Users\\surface\\Desktop\\classora-lms\\classora-lms\\accounts\\admin.py", "source_location": "L1", "weight": 1.0}, {"source": "c_users_surface_desktop_classora_lms_classora_lms_accounts_admin_py", "target": "django_contrib_auth_admin", "relation": "imports_from", "confidence": "EXTRACTED", "source_file": "C:\\Users\\surface\\Desktop\\classora-lms\\classora-lms\\accounts\\admin.py", "source_location": "L2", "weight": 1.0}, {"source": "c_users_surface_desktop_classora_lms_classora_lms_accounts_admin_py", "target": "c_users_surface_desktop_classora_lms_classora_lms_accounts_models_py", "relation": "imports_from", "confidence": "EXTRACTED", "source_file": "C:\\Users\\surface\\Desktop\\classora-lms\\classora-lms\\accounts\\admin.py", "source_location": "L4", "weight": 1.0}, {"source": "c_users_surface_desktop_classora_lms_classora_lms_accounts_admin_py", "target": "accounts_admin_instituteadmin", "relation": "contains", "confidence": "EXTRACTED", "source_file": "C:\\Users\\surface\\Desktop\\classora-lms\\classora-lms\\accounts\\admin.py", "source_location": "L8", "weight": 1.0}, {"source": "c_users_surface_desktop_classora_lms_classora_lms_accounts_admin_py", "target": "accounts_admin_customuseradmin", "relation": "contains", "confidence": "EXTRACTED", "source_file": "C:\\Users\\surface\\Desktop\\classora-lms\\classora-lms\\accounts\\admin.py", "source_location": "L14", "weight": 1.0}, {"source": "accounts_admin_customuseradmin", "target": "baseuseradmin", "relation": "inherits", "confidence": "EXTRACTED", "source_file": "C:\\Users\\surface\\Desktop\\classora-lms\\classora-lms\\accounts\\admin.py", "source_location": "L14", "weight": 1.0}], "raw_calls": []}